br_utilities-1.0.1.dist-info/licenses/LICENSE
br_utils/__init__.py
br_utils/br_utils.py
br_utils/cnpj/__init__.py
br_utils/cpf/__init__.py
br_utilities-1.0.1.dist-info/METADATA
br_utilities-1.0.1.dist-info/WHEEL
br_utilities-1.0.1.dist-info/top_level.txt
br_utilities-1.0.1.dist-info/RECORD
