Metadata-Version: 2.4
Name: br-utilities
Version: 1.0.1
Summary: Utility resources to deal with Brazilian-related data.
Author: Julio L. Muller
License-Expression: MIT
Project-URL: Homepage, https://cnpj-utils.vercel.app/
Project-URL: Source, https://github.com/LacusSolutions/br-utils-py
Project-URL: Tracker, https://github.com/LacusSolutions/br-utils-py/issues
Keywords: cpf,cnpj,cep,rg,state,city,validar,validador,validate,validation,formatar,format,gerar,gerador,generate,generator,pt-br,br
Classifier: Development Status :: 5 - Production/Stable
Classifier: Intended Audience :: Developers
Classifier: Natural Language :: English
Classifier: Natural Language :: Portuguese (Brazilian)
Classifier: Operating System :: MacOS :: MacOS X
Classifier: Operating System :: Microsoft :: Windows
Classifier: Operating System :: POSIX
Classifier: Operating System :: Unix
Classifier: Programming Language :: Python :: 3 :: Only
Classifier: Programming Language :: Python :: 3.10
Classifier: Programming Language :: Python :: 3.11
Classifier: Programming Language :: Python :: 3.12
Classifier: Programming Language :: Python :: 3.13
Classifier: Programming Language :: Python :: 3.14
Classifier: Topic :: Software Development :: Libraries
Classifier: Topic :: Utilities
Requires-Python: >=3.10
License-File: LICENSE
Requires-Dist: cnpj-utils<2.0.0,>=1.0.2
Requires-Dist: cpf-utils<2.0.0,>=1.0.1
Dynamic: license-file
